kling_26_motion_control/__init__.py
kling_26_motion_control-1769079.254.183.dist-info/licenses/LICENSE
kling_26_motion_control-1769079.254.183.dist-info/METADATA
kling_26_motion_control-1769079.254.183.dist-info/WHEEL
kling_26_motion_control-1769079.254.183.dist-info/top_level.txt
kling_26_motion_control-1769079.254.183.dist-info/RECORD
