Metadata-Version: 2.4
Name: kling-26-motion-control
Version: 1769079.254.183
Summary: High-quality integration for https://supermaker.ai/blog/how-to-use-kling-26-motion-control-ai-free-full-tutorial-ai-baby-dance-guide/
Home-page: https://supermaker.ai/blog/how-to-use-kling-26-motion-control-ai-free-full-tutorial-ai-baby-dance-guide/
Author: SuperMaker
Classifier: Programming Language :: Python :: 3
Classifier: License :: OSI Approved :: MIT License
Requires-Python: >=3.6
License-File: LICENSE
Dynamic: author
Dynamic: classifier
Dynamic: description
Dynamic: description-content-type
Dynamic: home-page
Dynamic: license-file
Dynamic: requires-python
Dynamic: summary
